dffml/__init__.py
dffml/__main__.py
dffml/base.py
dffml/high_level.py
dffml/log.py
dffml/noasync.py
dffml/plugins.py
dffml/record.py
dffml/version.py
dffml/cli/__init__.py
dffml/cli/cli.py
dffml/cli/config.py
dffml/cli/dataflow.py
dffml/cli/list.py
dffml/cli/log.py
dffml/cli/ml.py
dffml/configloader/__init__.py
dffml/configloader/configloader.py
dffml/configloader/json.py
dffml/db/__init__.py
dffml/db/base.py
dffml/db/sql.py
dffml/db/sqlite.py
dffml/df/__init__.py
dffml/df/base.py
dffml/df/exceptions.py
dffml/df/log.py
dffml/df/memory.py
dffml/df/multicomm.py
dffml/df/types.py
dffml/feature/__init__.py
dffml/feature/feature.py
dffml/feature/log.py
dffml/model/__init__.py
dffml/model/accuracy.py
dffml/model/log.py
dffml/model/model.py
dffml/model/slr.py
dffml/operation/__init__.py
dffml/operation/dataflow.py
dffml/operation/db.py
dffml/operation/io.py
dffml/operation/log.py
dffml/operation/mapping.py
dffml/operation/math.py
dffml/operation/model.py
dffml/operation/output.py
dffml/operation/preprocess.py
dffml/port/__init__.py
dffml/port/json.py
dffml/port/log.py
dffml/port/port.py
dffml/secret/__init__.py
dffml/secret/base.py
dffml/secret/ini.py
dffml/service/__init__.py
dffml/service/dev.py
dffml/skel/.gitignore
dffml/skel/common/.coveragerc
dffml/skel/common/.gitignore
dffml/skel/common/LICENSE
dffml/skel/common/MANIFEST.in
dffml/skel/common/pyproject.toml
dffml/skel/common/setup.cfg
dffml/skel/common/setup.py
dffml/skel/common/.github/workflows/testing.yml
dffml/skel/common/REPLACE_IMPORT_PACKAGE_NAME/__init__.py
dffml/skel/common/REPLACE_IMPORT_PACKAGE_NAME/version.py
dffml/skel/common/tests/__init__.py
dffml/skel/config/README.md
dffml/skel/config/entry_points.txt
dffml/skel/config/REPLACE_IMPORT_PACKAGE_NAME/configloader.py
dffml/skel/config/tests/test_config.py
dffml/skel/model/README.md
dffml/skel/model/entry_points.txt
dffml/skel/model/REPLACE_IMPORT_PACKAGE_NAME/myslr.py
dffml/skel/model/examples/example_myslr.py
dffml/skel/model/tests/test_integration.py
dffml-0.4.0.post2.dist-info/LICENSE
dffml-0.4.0.post2.dist-info/METADATA
dffml-0.4.0.post2.dist-info/WHEEL
dffml-0.4.0.post2.dist-info/entry_points.txt
dffml-0.4.0.post2.dist-info/top_level.txt
dffml-0.4.0.post2.dist-info/RECORD
