Metadata-Version: 2.1
Name: dffml
Version: 0.4.0.post2
Summary: Data Flow Facilitator for Machine Learning
Home-page: https://github.com/intel/dffml
Author: John Andersen
Author-email: john.s.andersen@intel.com
Maintainer: John Andersen
Maintainer-email: john.s.andersen@intel.com
License: MIT
Platform: UNKNOWN
Classifier: Development Status :: 3 - Alpha
Classifier: Intended Audience :: Developers
Classifier: License :: OSI Approved :: MIT License
Classifier: Natural Language :: English
Classifier: Operating System :: OS Independent
Classifier: Programming Language :: Python :: 3 :: Only
Classifier: Programming Language :: Python :: 3.7
Classifier: Programming Language :: Python :: Implementation :: CPython
Classifier: Programming Language :: Python :: Implementation :: PyPy
License-File: LICENSE
Provides-Extra: all
Requires-Dist: dffml-config-yaml ; extra == 'all'
Requires-Dist: dffml-config-image ; extra == 'all'
Requires-Dist: dffml-model-scratch ; extra == 'all'
Requires-Dist: dffml-model-scikit ; extra == 'all'
Requires-Dist: dffml-model-tensorflow ; extra == 'all'
Requires-Dist: dffml-model-tensorflow-hub ; extra == 'all'
Requires-Dist: dffml-model-vowpalWabbit ; extra == 'all'
Requires-Dist: dffml-model-xgboost ; extra == 'all'
Requires-Dist: dffml-model-pytorch ; extra == 'all'
Requires-Dist: dffml-model-spacy ; extra == 'all'
Requires-Dist: dffml-model-daal4py ; extra == 'all'
Requires-Dist: dffml-feature-git ; extra == 'all'
Requires-Dist: dffml-feature-auth ; extra == 'all'
Requires-Dist: dffml-operations-binsec ; extra == 'all'
Requires-Dist: dffml-operations-deploy ; extra == 'all'
Requires-Dist: dffml-operations-image ; extra == 'all'
Requires-Dist: dffml-operations-nlp ; extra == 'all'
Requires-Dist: dffml-service-http ; extra == 'all'
Requires-Dist: dffml-source-mysql ; extra == 'all'
Provides-Extra: configloaders
Requires-Dist: dffml-config-yaml ; extra == 'configloaders'
Requires-Dist: dffml-config-image ; extra == 'configloaders'
Provides-Extra: dev
Requires-Dist: coverage ; extra == 'dev'
Requires-Dist: codecov ; extra == 'dev'
Requires-Dist: sphinx (>=2.4.4) ; extra == 'dev'
Requires-Dist: sphinx-tabs (>=1.3.0) ; extra == 'dev'
Requires-Dist: sphinx-rtd-theme ; extra == 'dev'
Requires-Dist: recommonmark ; extra == 'dev'
Requires-Dist: black (==19.10b0) ; extra == 'dev'
Requires-Dist: jsbeautifier ; extra == 'dev'
Requires-Dist: twine ; extra == 'dev'
Requires-Dist: httptest (>=0.0.15) ; extra == 'dev'
Requires-Dist: Pillow (>=7.1.2) ; extra == 'dev'
Provides-Extra: models
Requires-Dist: dffml-model-scratch ; extra == 'models'
Requires-Dist: dffml-model-scikit ; extra == 'models'
Requires-Dist: dffml-model-tensorflow ; extra == 'models'
Requires-Dist: dffml-model-tensorflow-hub ; extra == 'models'
Requires-Dist: dffml-model-vowpalWabbit ; extra == 'models'
Requires-Dist: dffml-model-xgboost ; extra == 'models'
Requires-Dist: dffml-model-pytorch ; extra == 'models'
Requires-Dist: dffml-model-spacy ; extra == 'models'
Requires-Dist: dffml-model-daal4py ; extra == 'models'
Provides-Extra: operations
Requires-Dist: dffml-operations-binsec ; extra == 'operations'
Requires-Dist: dffml-operations-deploy ; extra == 'operations'
Requires-Dist: dffml-operations-image ; extra == 'operations'
Requires-Dist: dffml-operations-nlp ; extra == 'operations'
Requires-Dist: dffml-feature-git ; extra == 'operations'
Requires-Dist: dffml-feature-auth ; extra == 'operations'
Provides-Extra: services
Requires-Dist: dffml-service-http ; extra == 'services'
Provides-Extra: sources
Requires-Dist: dffml-source-mysql ; extra == 'sources'
